docx_properties/__init__.py
docx_properties/cli.py
docx_properties/core.py
docx_properties/field_updater.py
docx_properties-0.2.3.dist-info/METADATA
docx_properties-0.2.3.dist-info/WHEEL
docx_properties-0.2.3.dist-info/entry_points.txt
docx_properties-0.2.3.dist-info/top_level.txt
docx_properties-0.2.3.dist-info/RECORD
