Metadata-Version: 2.4
Name: docx_properties
Version: 0.2.3
Summary: Library for reading and editing properties in Word documents
Home-page: https://github.com/BegoByte/docx_properties
Author: BegoByte
Classifier: Programming Language :: Python :: 3
Classifier: License :: OSI Approved :: MIT License
Classifier: Operating System :: OS Independent
Requires-Python: >=3.6
Requires-Dist: lxml>=4.5.0
Requires-Dist: python-docx>=0.8.10
Dynamic: author
Dynamic: classifier
Dynamic: description
Dynamic: description-content-type
Dynamic: home-page
Dynamic: requires-dist
Dynamic: requires-python
Dynamic: summary
